flarelette/__init__.py
flarelette/app.py
flarelette/auth.py
flarelette/errors.py
flarelette/logging.py
flarelette/middleware.py
flarelette/py.typed
flarelette/request.py
flarelette/response.py
flarelette/router.py
flarelette/service.py
flarelette/validation.py
flarelette-0.1.2.dist-info/METADATA
flarelette-0.1.2.dist-info/WHEEL
flarelette-0.1.2.dist-info/top_level.txt
flarelette-0.1.2.dist-info/RECORD
