Metadata-Version: 2.4
Name: flarelette
Version: 0.1.2
Summary: Lightweight API framework for Cloudflare Python Workers - like Starlette but for Workers
Author-email: Chris Lyons <chris@chrislyons.dev>
License: MIT
Classifier: Development Status :: 3 - Alpha
Classifier: Intended Audience :: Developers
Classifier: License :: OSI Approved :: MIT License
Classifier: Programming Language :: Python :: 3
Classifier: Programming Language :: Python :: 3.11
Classifier: Programming Language :: Python :: 3.12
Classifier: Programming Language :: Python :: 3.13
Classifier: Topic :: Internet :: WWW/HTTP :: WSGI :: Application
Classifier: Topic :: Software Development :: Libraries :: Application Frameworks
Requires-Python: >=3.11
Requires-Dist: python-json-logger>=2.0.0
Provides-Extra: dev
Requires-Dist: pytest>=7.4.0; extra == "dev"
Requires-Dist: pytest-asyncio>=0.21.0; extra == "dev"
Requires-Dist: pytest-cov>=4.1.0; extra == "dev"
Requires-Dist: black>=23.0.0; extra == "dev"
Requires-Dist: ruff>=0.1.0; extra == "dev"
Requires-Dist: mypy>=1.7.0; extra == "dev"
